scss/__init__.py
scss/__main__.py
scss/ast.py
scss/calculator.py
scss/compiler.py
scss/config.py
scss/cssdefs.py
scss/errors.py
scss/legacy.py
scss/less2scss.py
scss/namespace.py
scss/rule.py
scss/scss_meta.py
scss/selector.py
scss/setup.py
scss/source.py
scss/tool.py
scss/types.py
scss/util.py
scss/extension/__init__.py
scss/extension/api.py
scss/extension/bootstrap.py
scss/extension/core.py
scss/extension/extra.py
scss/extension/fonts.py
scss/extension/compass/__init__.py
scss/extension/compass/gradients.py
scss/extension/compass/helpers.py
scss/extension/compass/images.py
scss/extension/compass/layouts.py
scss/extension/compass/sprites.py
scss/grammar/__init__.py
scss/grammar/_scanner.cpython-37m-darwin.so
scss/grammar/expression.py
scss/grammar/scanner.py
pyScss2-2.0.0.dist-info/LICENSE
pyScss2-2.0.0.dist-info/METADATA
pyScss2-2.0.0.dist-info/WHEEL
pyScss2-2.0.0.dist-info/entry_points.txt
pyScss2-2.0.0.dist-info/top_level.txt
pyScss2-2.0.0.dist-info/RECORD
