Metadata-Version: 2.1
Name: pyScss2
Version: 2.0.0
Summary: pyScss, a Scss compiler for Python
Home-page: http://github.com/e0ne/pyScss
Author: Ivan Kolodyazhny (e0ne)
Author-email: e0ne@e0ne.info
License: MIT
Download-URL: http://github.com/e0ne/pyScss/tarball/v2.0.0
Keywords: css oocss xcss sass scss less precompiler
Platform: UNKNOWN
Classifier: Development Status :: 5 - Production/Stable
Classifier: Intended Audience :: Developers
Classifier: License :: OSI Approved :: MIT License
Classifier: Operating System :: OS Independent
Classifier: Programming Language :: Python
Classifier: Programming Language :: Python :: 3
Classifier: Topic :: Software Development :: Code Generators
Classifier: Topic :: Text Processing :: Markup
Classifier: Topic :: Software Development :: Libraries :: Python Modules
Requires-Dist: six
